Workbook
Name Slicer_Months__Date: #N/A
Name Slicer_Product: #N/A
Name Slicer_Region: #N/A

Sheet Dashboard
M29: =Analysis!G4 -> Laptop | P29: =Analysis!H4 -> 66519499 | R29: =P29/SUM($P$29:$P$34) -> 0.46753125
M30: =Analysis!G5 -> Smartphone | P30: =Analysis!H5 -> 36192915 | R30: =P30/SUM($P$29:$P$34) -> 0.25438133
M31: =Analysis!G6 -> Monitor | P31: =Analysis!H6 -> 18707651 | R31: =P31/SUM($P$29:$P$34) -> 0.13148643
M32: =Analysis!G7 -> Printer | P32: =Analysis!H7 -> 13745452 | R32: =P32/SUM($P$29:$P$34) -> 0.096609694
M33: =Analysis!G8 -> Headphones | P33: =Analysis!H8 -> 4049370.6 | R33: =P33/SUM($P$29:$P$34) -> 0.028460938
M34: =Analysis!G9 -> Keyboard | P34: =Analysis!H9 -> 3063300.4 | R34: =P34/SUM($P$29:$P$34) -> 0.021530358

Sheet Analysis
A3: Total Revenue | C3: Total Units | E3: Average Order Value | G3: Top Product | H3: Revenue | J3: Months | K3: Sum of Revenue | M3: Region | N3: Revenue by Region
A4: 1.4227819e+08 | C4: 7729 | E4: 1976085.9 | G4: Laptop | H4: 66519499 | J4: 2025 | K4: 1.4227819e+08 | M4: East | N4: 29046048
G5: Smartphone | H5: 36192915 | J5: Jan | K5: 8669383.6 | M5: North | N5: 41659452
G6: Monitor | H6: 18707651 | J6: Feb | K6: 8616574.5 | M6: South | N6: 33766730
G7: Printer | H7: 13745452 | J7: Mar | K7: 15177720 | M7: West | N7: 37805958
G8: Headphones | H8: 4049370.6 | J8: Apr | K8: 12547128 | M8: Grand Total | N8: 1.4227819e+08
G9: Keyboard | H9: 3063300.4 | J9: May | K9: 12871781
G10: Grand Total | H10: 1.4227819e+08 | J10: Jun | K10: 11017565
J11: Jul | K11: 9976747.1
J12: Aug | K12: 15305530
J13: Sep | K13: 9944599.9
J14: Oct | K14: 7626723.4
J15: Nov | K15: 12762469
J16: Dec | K16: 17761968
J17: Grand Total | K17: 1.4227819e+08

Sheet Sales Data
A1: Date | B1: Product | C1: Region | D1: Units Sold | E1: Unit Price | F1: Discount | G1: Revenue | H1: Data Check
A2: 45658 | B2: Laptop | C2: West | D2: 60 | E2: 65000 | F2: 0.068276667 | G2: =D2*E2*(1-F2) -> 3633721 | H2: =IF(AND(D2>=1,E2>=0),"OK","CHECK") -> OK
A3: 45658 | B3: Smartphone | C3: East | D3: 138 | E3: 28000 | F3: 0.14735874 | G3: =D3*E3*(1-F3) -> 3294605.8 | H3: =IF(AND(D3>=1,E3>=0),"OK","CHECK") -> OK
A4: 45658 | B4: Monitor | C4: East | D4: 58 | E4: 16000 | F4: 0.090134456 | G4: =D4*E4*(1-F4) -> 844355.23 | H4: =IF(AND(D4>=1,E4>=0),"OK","CHECK") -> OK
A5: 45658 | B5: Keyboard | C5: West | D5: 77 | E5: 2500 | F5: 0.062212678 | G5: =D5*E5*(1-F5) -> 180524.06 | H5: =IF(AND(D5>=1,E5>=0),"OK","CHECK") -> OK
A6: 45658 | B6: Headphones | C6: West | D6: 103 | E6: 3500 | F6: 0.13425617 | G6: =D6*E6*(1-F6) -> 312100.65 | H6: =IF(AND(D6>=1,E6>=0),"OK","CHECK") -> OK
A7: 45658 | B7: Printer | C7: East | D7: 35 | E7: 12000 | F7: 0.037912362 | G7: =D7*E7*(1-F7) -> 404076.81 | H7: =IF(AND(D7>=1,E7>=0),"OK","CHECK") -> OK
A8: 45689 | B8: Laptop | C8: North | D8: 41 | E8: 65000 | F8: 0.13915122 | G8: =D8*E8*(1-F8) -> 2294162 | H8: =IF(AND(D8>=1,E8>=0),"OK","CHECK") -> OK
A9: 45689 | B9: Smartphone | C9: West | D9: 104 | E9: 28000 | F9: 0.14154338 | G9: =D9*E9*(1-F9) -> 2499825.7 | H9: =IF(AND(D9>=1,E9>=0),"OK","CHECK") -> OK
A10: 45689 | B10: Monitor | C10: North | D10: 147 | E10: 16000 | F10: 0.10206587 | G10: =D10*E10*(1-F10) -> 2111941.1 | H10: =IF(AND(D10>=1,E10>=0),"OK","CHECK") -> OK
A11: 45689 | B11: Keyboard | C11: East | D11: 69 | E11: 2500 | F11: 0.057636345 | G11: =D11*E11*(1-F11) -> 162557.73 | H11: =IF(AND(D11>=1,E11>=0),"OK","CHECK") -> OK
A12: 45689 | B12: Headphones | C12: South | D12: 73 | E12: 3500 | F12: 0.1390954 | G12: =D12*E12*(1-F12) -> 219961.12 | H12: =IF(AND(D12>=1,E12>=0),"OK","CHECK") -> OK
A13: 45689 | B13: Printer | C13: North | D13: 122 | E13: 12000 | F13: 0.09280951 | G13: =D13*E13*(1-F13) -> 1328126.9 | H13: =IF(AND(D13>=1,E13>=0),"OK","CHECK") -> OK
... A73: 45992 | B73: Printer | C73: North | D73: 170 | E73: 12000 | F73: 0.033652712 | G73: =D73*E73*(1-F73) -> 1971348.5 | H73: =IF(AND(D73>=1,E73>=0),"OK","CHECK") -> OK
